MANIFEST.in
README.rst
setup.py
clockcarlos/__init__.py
clockcarlos.egg-info/PKG-INFO
clockcarlos.egg-info/SOURCES.txt
clockcarlos.egg-info/dependency_links.txt
clockcarlos.egg-info/not-zip-safe
clockcarlos.egg-info/top_level.txt