Metadata-Version: 1.1
Name: clockcarlos
Version: 0.1
Summary: so you can have a visible timer on your terminal
Home-page: www.google.com
Author: TheTempest
Author-email: thetempest@gmail.com
License: MIT
Keywords: clock carlos timer hiphop iggy azalea white chicks
Platform: UNKNOWN
Classifier: Development Status :: 3 - Alpha
Classifier: License :: OSI Approved :: MIT License
Classifier: Programming Language :: Python :: 2.7
